MANIFEST.in
README.rst
setup.py
ckanext/__init__.py
ckanext/tagmanager/__init__.py
ckanext/tagmanager/commands.py
ckanext/tagmanager/controller.py
ckanext/tagmanager/db.py
ckanext/tagmanager/plugin.py
ckanext/tagmanager/public/css/default.css
ckanext/tagmanager/templates/header.html
ckanext/tagmanager/templates/tagmanager/delete_confirm.html
ckanext/tagmanager/templates/tagmanager/edit.html
ckanext/tagmanager/templates/tagmanager/index.html
ckanext/tagmanager/templates/tagmanager/index_merge_0.html
ckanext/tagmanager/templates/tagmanager/index_merge_1.html
ckanext/tagmanager/templates/tagmanager/index_merge_2.html
ckanext/tagmanager/templates/tagmanager/index_process_suggestions.html
ckanext/tagmanager/templates/tagmanager/merge_confirm.html
ckanext/tagmanager/templates/tagmanager/merge_form.html
ckanext/tagmanager/templates/tagmanager/snippets/menu.html
ckanext/tagmanager/templates/tagmanager/snippets/merge_preview.html
ckanext/tagmanager/templates/tagmanager/snippets/merge_suggestions.html
ckanext/tagmanager/templates/tagmanager/snippets/merge_tags_form.html
ckanext/tagmanager/templates/tagmanager/snippets/process_suggestions.html
ckanext/tagmanager/templates/tagmanager/snippets/tags_list.html
ckanext/tagmanager/templates/tagmanager/snippets/tags_list_with_remove.html
ckanext/tagmanager/templates/tagmanager/snippets/tags_stats.html
ckanext/tagmanager/tests/__init__.py
ckanext/tagmanager/tests/test_plugin.py
ckanext_tagmanager.egg-info/PKG-INFO
ckanext_tagmanager.egg-info/SOURCES.txt
ckanext_tagmanager.egg-info/dependency_links.txt
ckanext_tagmanager.egg-info/entry_points.txt
ckanext_tagmanager.egg-info/top_level.txt