Metadata-Version: 1.1
Name: ckanext-tagmanager
Version: 0.0.2
Summary: Tag management for CKAN portals
Home-page: https://github.com/alantygel/ckanext-tagmanager
Author: Alan Tygel
Author-email: alantygel@gmail.com
License: AGPL
Keywords: CKAN tag,management,organization,tag merging,tag cleansing
Platform: UNKNOWN
Classifier: Development Status :: 4 - Beta
Classifier: License :: OSI Approved :: GNU Affero General Public License v3 or later (AGPLv3+)
Classifier: Programming Language :: Python :: 2.6
Classifier: Programming Language :: Python :: 2.7
